napari_bee_annotator/__init__.py
napari_bee_annotator/_reader.py
napari_bee_annotator/_version.py
napari_bee_annotator/_widget.py
napari_bee_annotator/_writer.py
napari_bee_annotator/napari.yaml
napari_bee_annotator/_tests/__init__.py
napari_bee_annotator/_tests/test_reader_writer.py
napari_bee_annotator/_tests/test_widget.py
napari_bee_annotator-0.0.1.dist-info/LICENSE
napari_bee_annotator-0.0.1.dist-info/METADATA
napari_bee_annotator-0.0.1.dist-info/WHEEL
napari_bee_annotator-0.0.1.dist-info/entry_points.txt
napari_bee_annotator-0.0.1.dist-info/top_level.txt
napari_bee_annotator-0.0.1.dist-info/RECORD
